image_distillation/__init__.py
image_distillation/main.py
image_distillation-0.1.6.dist-info/METADATA
image_distillation-0.1.6.dist-info/WHEEL
image_distillation-0.1.6.dist-info/top_level.txt
image_distillation-0.1.6.dist-info/RECORD
